survey_stats_mabaraty/__init__.py
survey_stats_mabaraty/basic_model.py
survey_stats_mabaraty/data_process.py
survey_stats_mabaraty/date.py
survey_stats_mabaraty/functions.py
survey_stats_mabaraty/keyboard.py
survey_stats_mabaraty/shakhesban.txt
survey_stats_mabaraty/shutdown.py
survey_stats_mabaraty/sound.py
survey_stats_mabaraty/test.py
survey_stats_mabaraty/text_to_speech.py
survey_stats_mabaraty/classification/__init__.py
survey_stats_mabaraty/classification/tree_based_regression-last_version.py
survey_stats_mabaraty/classification/tree_based_regression.py
survey_stats_mabaraty/linear_regressions/__init__.py
survey_stats_mabaraty/linear_regressions/ols.py
survey_stats_mabaraty/sklearn/__init__.py
survey_stats_mabaraty/sklearn/logit.py
survey_stats_mabaraty/sklearn/multinominal_logit.py
survey_stats_mabaraty/sklearn/ols.py
survey_stats_mabaraty/statsmodels/__init__.py
survey_stats_mabaraty/statsmodels/logit.py
survey_stats_mabaraty/statsmodels/multinominal_logit.py
survey_stats_mabaraty-1.1.23.dist-info/METADATA
survey_stats_mabaraty-1.1.23.dist-info/WHEEL
survey_stats_mabaraty-1.1.23.dist-info/licenses/LICENSE
survey_stats_mabaraty-1.1.23.dist-info/RECORD
