Metadata-Version: 2.4
Name: survey_stats_mabaraty
Version: 1.1.23
Summary: survey_stats a simple and powerfull package for data processing and statistics
Project-URL: Homepage, https://github.com/mohammad-ali-barati
Project-URL: Issues, https://github.com/pypa/sampleproject//survey_stats
Author-email: Mohammad Ali Barati <mabaraty@gmail.com>
License-File: LICENSE
Classifier: License :: OSI Approved :: MIT License
Classifier: Operating System :: OS Independent
Classifier: Programming Language :: Python :: 3
Requires-Python: >=3.7
Requires-Dist: jdatetime
Requires-Dist: matplotlib
Requires-Dist: msaccessdb
Requires-Dist: numpy
Requires-Dist: openpyxl
Requires-Dist: pyodbc
Requires-Dist: requests
Requires-Dist: scikit-learn
Requires-Dist: scipy
Requires-Dist: statsmodels
Requires-Dist: xlrd
